aquarius/__init__.py
aquarius/config.py
aquarius/constants.py
aquarius/log.py
aquarius/myapp.py
aquarius/run.py
aquarius/app/__init__.py
aquarius/app/assets.py
aquarius/app/auth_util.py
aquarius/app/dao.py
aquarius/app/pool_helper.py
aquarius/app/pools.py
aquarius/app/util.py
ocean_aquarius-2.2.2.dist-info/LICENSE
ocean_aquarius-2.2.2.dist-info/METADATA
ocean_aquarius-2.2.2.dist-info/WHEEL
ocean_aquarius-2.2.2.dist-info/top_level.txt
ocean_aquarius-2.2.2.dist-info/RECORD
