Metadata-Version: 2.1
Name: ocean-aquarius
Version: 2.2.2
Summary: 🐳 Ocean aquarius.
Home-page: https://github.com/oceanprotocol/aquarius
Author: leucothia
Author-email: devops@oceanprotocol.com
License: Apache Software License 2.0
Keywords: ocean-aquarius
Platform: UNKNOWN
Classifier: Development Status :: 2 - Pre-Alpha
Classifier: Intended Audience :: Developers
Classifier: License :: OSI Approved :: Apache Software License
Classifier: Natural Language :: English
Classifier: Programming Language :: Python :: 3.6
Classifier: Programming Language :: Python :: 3.7
Requires-Dist: coloredlogs (==14.0)
Requires-Dist: Flask (==1.1.2)
Requires-Dist: Flask-Cors (==3.0.9)
Requires-Dist: flask-swagger (==0.2.14)
Requires-Dist: flask-swagger-ui (==3.36.0)
Requires-Dist: Jinja2 (>=2.10.1)
Requires-Dist: requests (>=2.21.0)
Requires-Dist: gunicorn (==20.0.4)
Requires-Dist: oceandb-driver-interface (==0.2.0)
Requires-Dist: oceandb-mongodb-driver (==0.2.2)
Requires-Dist: oceandb-elasticsearch-driver (==0.4.4)
Requires-Dist: PyYAML (==5.3.1)
Requires-Dist: pytz (==2020.4)
Requires-Dist: plecos (==1.1.0)
Requires-Dist: ocean-lib (==0.5.3)
Requires-Dist: eciespy
Requires-Dist: gevent
Provides-Extra: dev
Requires-Dist: bumpversion (==0.6.0) ; extra == 'dev'
Requires-Dist: pkginfo (==1.6.1) ; extra == 'dev'
Requires-Dist: twine (==3.2.0) ; extra == 'dev'
Requires-Dist: watchdog (==0.10.4) ; extra == 'dev'
Requires-Dist: plecos (==1.1.0) ; extra == 'dev'
Requires-Dist: Flask (==1.1.2) ; extra == 'dev'
Requires-Dist: codacy-coverage (==1.3.11) ; extra == 'dev'
Requires-Dist: coverage (==5.3) ; extra == 'dev'
Requires-Dist: mccabe (==0.6.1) ; extra == 'dev'
Requires-Dist: pylint (==2.6.0) ; extra == 'dev'
Requires-Dist: pytest ; extra == 'dev'
Requires-Dist: tox ; extra == 'dev'
Provides-Extra: test
Requires-Dist: plecos (==1.1.0) ; extra == 'test'
Requires-Dist: Flask (==1.1.2) ; extra == 'test'
Requires-Dist: codacy-coverage (==1.3.11) ; extra == 'test'
Requires-Dist: coverage (==5.3) ; extra == 'test'
Requires-Dist: mccabe (==0.6.1) ; extra == 'test'
Requires-Dist: pylint (==2.6.0) ; extra == 'test'
Requires-Dist: pytest ; extra == 'test'
Requires-Dist: tox ; extra == 'test'
